{"name":"Tarjeta no valida","id":"quiero-ingresar-a-la-pagina-principal-de-travelocity;tarjeta-no-valida","testSteps":[{"number":1,"description":"When el usuario ingresa un numero de  tarjeta en informacon de pago","duration":345,"startTime":"2021-04-12T18:40:14.164-05:00[America/Bogota]","result":"SUCCESS","precondition":false,"level":0},{"number":2,"description":"Then visualiza un mensaje que el numero de la tarjeta no es valido","duration":358,"startTime":"2021-04-12T18:40:14.509-05:00[America/Bogota]","result":"SUCCESS","precondition":false,"level":0}],"userStory":{"id":"quiero-ingresar-a-la-pagina-principal-de-travelocity","storyName":"Quiero ingresar a la pagina principal de travelocity","path":"src/test/resources/features/manuales/PaginaPrincipal.feature","type":"feature"},"featureTag":{"name":"Manuales/Quiero ingresar a la pagina principal de travelocity","type":"feature"},"title":"Tarjeta no valida","tags":[{"name":"8","type":"UserStory-Manual"},{"name":"Manuales","type":"capability"},{"name":"Manuales/Quiero ingresar a la pagina principal de travelocity","type":"feature"}],"startTime":"2021-04-12T18:40:14.160-05:00[America/Bogota]","duration":710,"projectKey":"","manual":false,"testSource":"Cucumber","result":"SUCCESS"}